django_groups_cache-1.0.2.dist-info/DESCRIPTION.rst
django_groups_cache-1.0.2.dist-info/METADATA
django_groups_cache-1.0.2.dist-info/RECORD
django_groups_cache-1.0.2.dist-info/WHEEL
django_groups_cache-1.0.2.dist-info/metadata.json
django_groups_cache-1.0.2.dist-info/top_level.txt
groups_cache/__init__.py
groups_cache/apps.py
groups_cache/compat.py
groups_cache/default_settings.py
groups_cache/middleware.py
groups_cache/models.py
groups_cache/signals.py
groups_cache/urls.py
groups_cache/utils.py
groups_cache/views.py
groups_cache/static/css/groups_cache.css
groups_cache/static/js/groups_cache.js
groups_cache/templates/groups_cache/base.html
groups_cache/templatetags/__init__.py
groups_cache/templatetags/has_group.py
