Metadata-Version: 2.0
Name: django-groups-cache
Version: 1.0.2
Summary: Caches the groups a user is in so requests don't have to make calls to the database to check group status.
Home-page: https://github.com/audiolion/django-groups-cache
Author: Ryan Castner
Author-email: castner.rr@gmail.com
License: MIT
Keywords: django-groups-cache
Platform: UNKNOWN
Classifier: Development Status :: 4 - Beta
Classifier: Framework :: Django
Classifier: Framework :: Django :: 1.8
Classifier: Framework :: Django :: 1.11
Classifier: Framework :: Django :: 2.0
Classifier: Intended Audience :: Developers
Classifier: License :: OSI Approved :: MIT License
Classifier: Natural Language :: English
Classifier: Programming Language :: Python :: 2
Classifier: Programming Language :: Python :: 2.7
Classifier: Programming Language :: Python :: 3
Classifier: Programming Language :: Python :: 3.4
Classifier: Programming Language :: Python :: 3.5
Classifier: Programming Language :: Python :: 3.6
